xfoil/__init__.py
xfoil/libxfoil.dll
xfoil/model.py
xfoil/test.py
xfoil/xfoil.py
xfoil-1.1.1.dist-info/LICENSE
xfoil-1.1.1.dist-info/METADATA
xfoil-1.1.1.dist-info/WHEEL
xfoil-1.1.1.dist-info/top_level.txt
xfoil-1.1.1.dist-info/RECORD
