Metadata-Version: 2.1
Name: xfoil
Version: 1.1.1
Summary: Stripped down version of XFOIL as compiled python module 
Home-page: https://github.com/daniel-de-vries/xfoil-python
Author: Daniël de Vries
Author-email: contact@daniel-de-vries.com
License: GNU General Public License v3 or later (GPLv3+)
Download-URL: https://github.com/daniel-de-vries/xfoil-python/tarball/1.1.1
Keywords: xfoil airfoil aerodynamic analysis
Platform: UNKNOWN
Classifier: Development Status :: 3 - Alpha
Classifier: Intended Audience :: Science/Research
Classifier: License :: OSI Approved :: GNU General Public License v3 or later (GPLv3+)
Classifier: Natural Language :: English
Classifier: Operating System :: MacOS :: MacOS X
Classifier: Operating System :: POSIX :: Linux
Classifier: Operating System :: Microsoft :: Windows
Classifier: Programming Language :: Fortran
Classifier: Programming Language :: Python :: 3 :: Only
Classifier: Topic :: Scientific/Engineering
